ovos_stt_plugin_projectAINA/__init__.py
ovos_stt_plugin_projectAINA/version.py
ovos_stt_plugin_projectAINA_remote-0.0.2.dist-info/METADATA
ovos_stt_plugin_projectAINA_remote-0.0.2.dist-info/WHEEL
ovos_stt_plugin_projectAINA_remote-0.0.2.dist-info/entry_points.txt
ovos_stt_plugin_projectAINA_remote-0.0.2.dist-info/top_level.txt
ovos_stt_plugin_projectAINA_remote-0.0.2.dist-info/zip-safe
ovos_stt_plugin_projectAINA_remote-0.0.2.dist-info/RECORD
